MANIFEST.in
README
README.md
setup.py
TempestParser.egg-info/PKG-INFO
TempestParser.egg-info/SOURCES.txt
TempestParser.egg-info/dependency_links.txt
TempestParser.egg-info/entry_points.txt
TempestParser.egg-info/not-zip-safe
TempestParser.egg-info/requires.txt
TempestParser.egg-info/top_level.txt
tempest_parser/__init__.py
tempest_parser/const.py
tempest_parser/tparser.py
tempest_parser/etc/tempest-parser.conf
tempest_parser/manager/__init__.py
tempest_parser/manager/importers.py
tempest_parser/manager/structs.py
tempest_parser/manager/test_manager.py
tempest_parser/parser/__init__.py
tempest_parser/parser/parser_strings.py
tempest_parser/parser/tempest_log_parser.py
tempest_parser/reports/__init__.py
tempest_parser/reports/csv_reporter.py
tempest_parser/reports/reporter.py
tempest_parser/res/all_sanity.list
tempest_parser/res/all_tests_tag_18.list
tempest_parser/templates/tempest_errors_report.html
tempest_parser/templates/tempest_trending_report.html
tempest_parser/utils/__init__.py
tempest_parser/utils/config.py
tempest_parser/utils/file.py