Metadata-Version: 1.1
Name: TempestParser
Version: 0.2.51
Summary: Tempest Parser tool used to generate trending reports out of various result formats openstack/tempest produces: pytest's CLI, Rally's JSON, CSV (two types) and Subunit (binary stream and XML export).
Home-page: https://github.com/savex/tempest-parser
Author: Alex Savatieiev
Author-email: a.savex@gmail.com
License: Apache Licence, version 2
Keywords: QA,tempest,openstack,html,report
Platform: UNKNOWN
Classifier: Programming Language :: Python
Classifier: Programming Language :: Python :: 2.7
